{
  "user": {
    "id": 202001,
    "username": "DongWook Kim",
    "password": 123123
  },
  "board": {
    "id": 1,
    "board_name": "개발자 동욱",
    "description": "첫 번째 기본보드",
    "collaborators": [
      202001,
      202002
    ],
    "recent_open": "2020-09-09 thr 13:21:12",
    "is_starred": false,
    "backgrounds": {
      "color": "rgb(0, 121, 191)",
      "image": "https://images.unsplash.com/25/peak.jpg?ixlib=rb-1.2.1&ixid=eyJhcHBfaWQiOjEyMDd9&auto=format&fit=crop&w=1050&q=80"
    },
    "activity": []
  },
  "lists": [
    {
      "id": "list-1",
      "name": "fdsafds",
      "board_id": 1,
      "user_id": 1
    },
    {
      "id": "list-2",
      "name": "sdafsd",
      "board_id": 1,
      "user_id": 1
    },
    {
      "id": "list-3",
      "name": "asfdsa",
      "board_id": 1,
      "user_id": 1
    }
  ],
  "cards": [
    {
      "id": 1,
      "card_name": "치과가기",
      "description": "이것은 기본카드",
      "list_id": 1,
      "labels": [
        "development"
      ],
      "members": [
        "dongwook",
        "junseon"
      ],
      "due_date": "2020.6.18",
      "sticker": [
        {
          "name": "star"
        }
      ]
    },
    {
      "id": 2,
      "description": "이것은 기본카드",
      "card_name": "학원상담",
      "list_id": 2,
      "labels": [
        "development"
      ],
      "members": [
        "dongwook",
        "junseon"
      ],
      "due_date": "2020.6.18",
      "sticker": [
        {
          "name": "star"
        }
      ]
    },
    {
      "id": 3,
      "description": "이것은 기본카드",
      "card_name": "큰집 인사",
      "list_id": 2,
      "labels": [
        "development"
      ],
      "members": [
        "dongwook",
        "junseon"
      ],
      "due_date": "2020.6.18",
      "sticker": [
        {
          "name": "star"
        }
      ]
    }
  ]
}